setup.cfg
setup.py
ajax/__init__.py
ajax/decorators.py
ajax/encoders.py
ajax/endpoints.py
ajax/exceptions.py
ajax/models.py
ajax/signals.py
ajax/urls.py
ajax/views.py
ajax.egg-info/PKG-INFO
ajax.egg-info/SOURCES.txt
ajax.egg-info/dependency_links.txt
ajax.egg-info/not-zip-safe
ajax.egg-info/requires.txt
ajax.egg-info/top_level.txt
ajax/middleware/DebugToolbar.py
ajax/middleware/__init__.py
tests/__init__.py
tests/manage.py
tests/settings.py
tests/urls.py
tests/example/__init__.py
tests/example/endpoints.py
tests/example/models.py
tests/example/tests.py
tests/example/views.py