Metadata-Version: 1.0
Name: ajax
Version: 1.1.0
Summary: A simple framework for creating AJAX endpoints in Django.
Home-page: https://github.com/joestump/django-ajax
Author: Joseph C. Stump
Author-email: joe@stu.mp
License: BSD
Keywords: django,ajax
Platform: UNKNOWN
Classifier: Programming Language :: Python
Classifier: Topic :: Software Development :: Libraries :: Python Modules
Classifier: Framework :: Django
Classifier: Environment :: Web Environment
